counter.v
module counter(
    input clk, reset,
    output reg [3:0] count
);
    always @(posedge clk or posedge reset) begin
        if (reset)
            count <= 4'b0000;
        else
            count <= count + 1;
    end
endmodule

counter_tb.v
module counter_tb;
    reg clk, reset;
    wire [3:0] count;

    counter uut(.clk(clk), .reset(reset), .count(count));

    initial clk = 0;
    always #5 clk = ~clk;

    initial begin
        $dumpfile("counter.vcd");
        $dumpvars(0, counter_tb);
        reset = 1;
        #10 reset = 0;
        #1000 $finish;
    end
endmodule

counter.vcd
$date
	Sun Apr 05 12:59:09 2026
$end
$version
	Icarus Verilog
$end
$timescale
	1s
$end
$scope module counter_tb $end
$var wire 4 ! count [3:0] $end
$var reg 1 " clk $end
$var reg 1 # reset $end
$scope module uut $end
$var wire 1 " clk $end
$var wire 1 # reset $end
$var reg 4 $ count [3:0] $end
$upscope $end
$upscope $end
$enddefinitions $end
$comment Show the parameter values. $end
$dumpall
$end
#0
$dumpvars
b0 $
1#
0"
b0 !
$end
#5
1"
#10
0"
0#
#15
b1 !
b1 $
1"
#20
0"
#25
b10 !
b10 $
1"
#30
0"
#35
b11 !
b11 $
1"
#40
0"
#45
b100 !
b100 $
1"
#50
0"
#55
b101 !
b101 $
1"
#60
0"
#65
b110 !
b110 $
1"
#70
0"
#75
b111 !
b111 $
1"
#80
0"
#85
b1000 !
b1000 $
1"
#90
0"
#95
b1001 !
b1001 $
1"
#100
0"
#105
b1010 !
b1010 $
1"
#110
0"
#115
b1011 !
b1011 $
1"
#120
0"
#125
b1100 !
b1100 $
1"
#130
0"
#135
b1101 !
b1101 $
1"
#140
0"
#145
b1110 !
b1110 $
1"
#150
0"
#155
b1111 !
b1111 $
1"
#160
0"
#165
b0 !
b0 $
1"
#170
0"
#175
b1 !
b1 $
1"
#180
0"
#185
b10 !
b10 $
1"
#190
0"
#195
b11 !
b11 $
1"
#200
0"
#205
b100 !
b100 $
1"
#210
0"
#215
b101 !
b101 $
1"
#220
0"
#225
b110 !
b110 $
1"
#230
0"
#235
b111 !
b111 $
1"
#240
0"
#245
b1000 !
b1000 $
1"
#250
0"
#255
b1001 !
b1001 $
1"
#260
0"
#265
b1010 !
b1010 $
1"
#270
0"
#275
b1011 !
b1011 $
1"
#280
0"
#285
b1100 !
b1100 $
1"
#290
0"
#295
b1101 !
b1101 $
1"
#300
0"
#305
b1110 !
b1110 $
1"
#310
0"
#315
b1111 !
b1111 $
1"
#320
0"
#325
b0 !
b0 $
1"
#330
0"
#335
b1 !
b1 $
1"
#340
0"
#345
b10 !
b10 $
1"
#350
0"
#355
b11 !
b11 $
1"
#360
0"
#365
b100 !
b100 $
1"
#370
0"
#375
b101 !
b101 $
1"
#380
0"
#385
b110 !
b110 $
1"
#390
0"
#395
b111 !
b111 $
1"
#400
0"
#405
b1000 !
b1000 $
1"
#410
0"
#415
b1001 !
b1001 $
1"
#420
0"
#425
b1010 !
b1010 $
1"
#430
0"
#435
b1011 !
b1011 $
1"
#440
0"
#445
b1100 !
b1100 $
1"
#450
0"
#455
b1101 !
b1101 $
1"
#460
0"
#465
b1110 !
b1110 $
1"
#470
0"
#475
b1111 !
b1111 $
1"
#480
0"
#485
b0 !
b0 $
1"
#490
0"
#495
b1 !
b1 $
1"
#500
0"
#505
b10 !
b10 $
1"
#510
0"
#515
b11 !
b11 $
1"
#520
0"
#525
b100 !
b100 $
1"
#530
0"
#535
b101 !
b101 $
1"
#540
0"
#545
b110 !
b110 $
1"
#550
0"
#555
b111 !
b111 $
1"
#560
0"
#565
b1000 !
b1000 $
1"
#570
0"
#575
b1001 !
b1001 $
1"
#580
0"
#585
b1010 !
b1010 $
1"
#590
0"
#595
b1011 !
b1011 $
1"
#600
0"
#605
b1100 !
b1100 $
1"
#610
0"
#615
b1101 !
b1101 $
1"
#620
0"
#625
b1110 !
b1110 $
1"
#630
0"
#635
b1111 !
b1111 $
1"
#640
0"
#645
b0 !
b0 $
1"
#650
0"
#655
b1 !
b1 $
1"
#660
0"
#665
b10 !
b10 $
1"
#670
0"
#675
b11 !
b11 $
1"
#680
0"
#685
b100 !
b100 $
1"
#690
0"
#695
b101 !
b101 $
1"
#700
0"
#705
b110 !
b110 $
1"
#710
0"
#715
b111 !
b111 $
1"
#720
0"
#725
b1000 !
b1000 $
1"
#730
0"
#735
b1001 !
b1001 $
1"
#740
0"
#745
b1010 !
b1010 $
1"
#750
0"
#755
b1011 !
b1011 $
1"
#760
0"
#765
b1100 !
b1100 $
1"
#770
0"
#775
b1101 !
b1101 $
1"
#780
0"
#785
b1110 !
b1110 $
1"
#790
0"
#795
b1111 !
b1111 $
1"
#800
0"
#805
b0 !
b0 $
1"
#810
0"
#815
b1 !
b1 $
1"
#820
0"
#825
b10 !
b10 $
1"
#830
0"
#835
b11 !
b11 $
1"
#840
0"
#845
b100 !
b100 $
1"
#850
0"
#855
b101 !
b101 $
1"
#860
0"
#865
b110 !
b110 $
1"
#870
0"
#875
b111 !
b111 $
1"
#880
0"
#885
b1000 !
b1000 $
1"
#890
0"
#895
b1001 !
b1001 $
1"
#900
0"
#905
b1010 !
b1010 $
1"
#910
0"
#915
b1011 !
b1011 $
1"
#920
0"
#925
b1100 !
b1100 $
1"
#930
0"
#935
b1101 !
b1101 $
1"
#940
0"
#945
b1110 !
b1110 $
1"
#950
0"
#955
b1111 !
b1111 $
1"
#960
0"
#965
b0 !
b0 $
1"
#970
0"
#975
b1 !
b1 $
1"
#980
0"
#985
b10 !
b10 $
1"
#990
0"
#995
b11 !
b11 $
1"
#1000
0"
#1005
b100 !
b100 $
1"
